fossology/__init__.py
fossology/__main__.py
fossology/enums.py
fossology/exceptions.py
fossology/folders.py
fossology/foss_cli.py
fossology/groups.py
fossology/items.py
fossology/jobs.py
fossology/license.py
fossology/obj.py
fossology/report.py
fossology/search.py
fossology/uploads.py
fossology/users.py
fossology-3.3.2.dist-info/LICENSE.md
fossology-3.3.2.dist-info/METADATA
fossology-3.3.2.dist-info/WHEEL
fossology-3.3.2.dist-info/entry_points.txt
fossology-3.3.2.dist-info/RECORD
