Metadata-Version: 2.3
Name: fossology
Version: 3.3.2
Summary: A library to automate Fossology from Python scripts
License: MIT
Author: Marion Deveaud
Author-email: marion.deveaud@siemens.com
Requires-Python: >=3.10,<4.0
Classifier: Development Status :: 5 - Production/Stable
Classifier: Environment :: Web Environment
Classifier: Intended Audience :: Developers
Classifier: License :: OSI Approved :: MIT License
Classifier: Natural Language :: English
Classifier: Operating System :: OS Independent
Classifier: Programming Language :: Python :: 3
Classifier: Programming Language :: Python :: 3.10
Classifier: Programming Language :: Python :: 3.11
Classifier: Programming Language :: Python :: 3.12
Classifier: Programming Language :: Python :: 3.13
Classifier: Programming Language :: Python :: 3 :: Only
Requires-Dist: click (>=8.2.1,<9.0.0)
Requires-Dist: poethepoet (>=0.21.1,<0.22.0)
Requires-Dist: requests (>=2.32.3,<3.0.0)
Requires-Dist: requests-toolbelt (>=1.0.0,<2.0.0)
Requires-Dist: tenacity (>=9.1.2,<10.0.0)
Requires-Dist: types-requests (>=2.32.0.2,<3.0.0.0)
Project-URL: Homepage, https://github.com/fossology/fossology-python
Project-URL: Repository, https://github.com/fossology/fossology-python
